pypaya_json/__init__.py
pypaya_json/core.py
pypaya_json-0.3.0.dist-info/LICENSE
pypaya_json-0.3.0.dist-info/METADATA
pypaya_json-0.3.0.dist-info/WHEEL
pypaya_json-0.3.0.dist-info/RECORD
